clp_logging/__init__.py
clp_logging/auto_generated_kv_pairs_utils.py
clp_logging/handlers.py
clp_logging/protocol.py
clp_logging/py.typed
clp_logging/utils.py
clp_logging-0.0.15.dist-info/LICENSE
clp_logging-0.0.15.dist-info/METADATA
clp_logging-0.0.15.dist-info/WHEEL
clp_logging-0.0.15.dist-info/top_level.txt
clp_logging-0.0.15.dist-info/RECORD
