Metadata-Version: 2.1
Name: clp_logging
Version: 0.0.15
Summary: Logging/encoding/decoding using CLP's IR stream format
Author-email: david lion <david.lion@yscope.com>
License: Apache License 2.0
Project-URL: Homepage, https://github.com/y-scope/clp-loglib-py
Project-URL: Bug Tracker, https://github.com/y-scope/clp-loglib-py/issues
Classifier: License :: OSI Approved :: Apache Software License
Requires-Python: >=3.7
License-File: LICENSE
Requires-Dist: clp-ffi-py >=0.0.14
Requires-Dist: typing-extensions >=3.7.4
Requires-Dist: zstandard >=0.18.0
Requires-Dist: tzlocal ==5.1 ; python_version < "3.8"
Requires-Dist: backports.zoneinfo >=0.2.1 ; python_version < "3.9"
Requires-Dist: tzlocal >=5.2 ; python_version >= "3.8"
Provides-Extra: dev
Requires-Dist: black >=24.4.0 ; extra == 'dev'
Requires-Dist: build >=0.8.0 ; extra == 'dev'
Requires-Dist: docformatter >=1.7.5 ; extra == 'dev'
Requires-Dist: mypy >=1.9.0 ; extra == 'dev'
Requires-Dist: ruff >=0.3.7 ; extra == 'dev'
Requires-Dist: types-python-dateutil >=2.8.19.2 ; extra == 'dev'
Provides-Extra: test
Requires-Dist: smart-open ==6.4.0 ; extra == 'test'
